[
  {
    "name": "Van Gogh - An Immersive Story",
    "url": " https://in.bookmyshow.com/events/van-gogh-an-immersive-story/ET00440776",
    "timestamp": "2025-06-11 08:36:42",
    "scraped_at": "2025-06-11T08:36:42.263470",
    "image": "https://assets-in.bmscdn.com/discovery-catalog/events/tr:w-400,h-600,bg-CCCCCC:w-400.0,h-660.0,cm-pad_resize,bg-000000,fo-top:l-text,ie-V2VkLCAxMSBKdW4gb253YXJkcw%3D%3D,fs-29,co-FFFFFF,ly-612,lx-24,pa-8_0_0_0,l-end/et00440776-mguaamplyv-portrait.jpg"
  },
  {
    "name": "So Mini Things with Shraddha Jain- One Last Time",
    "url": " https://in.bookmyshow.com/events/so-mini-things-with-shraddha-jain-one-last-time/ET00445356",
    "timestamp": "2025-06-11 08:36:42",
    "scraped_at": "2025-06-11T08:36:42.319593",
    "image": "https://assets-in.bmscdn.com/discovery-catalog/events/tr:w-400,h-600,bg-CCCCCC:w-400.0,h-660.0,cm-pad_resize,bg-000000,fo-top:l-text,ie-U2F0LCAyOCBKdW4%3D,fs-29,co-FFFFFF,ly-612,lx-24,pa-8_0_0_0,l-end/et00445356-kppysxqfrq-portrait.jpg"
  },
  {
    "name": "Jo Bolta Hai Wahi Hota Hai feat Harsh Gujral",
    "url": " https://in.bookmyshow.com/events/jo-bolta-hai-wohi-hota-hai-feat-harsh-gujral/ET00145294",
    "timestamp": "2025-06-11 08:36:42",
    "scraped_at": "2025-06-11T08:36:42.355281",
    "image": "https://assets-in.bmscdn.com/discovery-catalog/events/tr:w-400,h-600,bg-CCCCCC:w-400.0,h-660.0,cm-pad_resize,bg-000000,fo-top:l-text,ie-TW9uLCAyMyBKdW4%3D,fs-29,co-FFFFFF,ly-612,lx-24,pa-8_0_0_0,l-end/et00145294-ybbegwraap-portrait.jpg"
  },
  {
    "name": "Kisi Ko Batana Mat By Anubhav Singh Bassi - Delhi",
    "url": " https://in.bookmyshow.com/events/kisi-ko-batana-mat-by-anubhav-singh-bassi/ET00383732",
    "timestamp": "2025-06-11 08:36:42",
    "scraped_at": "2025-06-11T08:36:42.393996",
    "image": "https://assets-in.bmscdn.com/discovery-catalog/events/tr:w-400,h-600,bg-CCCCCC:w-400.0,h-660.0,cm-pad_resize,bg-000000,fo-top:l-text,ie-U2F0LCAyIEF1Zw%3D%3D,fs-29,co-FFFFFF,ly-612,lx-24,pa-8_0_0_0,l-end/et00383732-mlgxqtbqst-portrait.jpg"
  },
  {
    "name": "KAL KI CHINTA NHI KARTA FT. RAVI GUPTA",
    "url": " https://in.bookmyshow.com/events/kal-ki-chinta-nhi-karta-ft-ravi-gupta/ET00439601",
    "timestamp": "2025-06-11 08:36:42",
    "scraped_at": "2025-06-11T08:36:42.431078",
    "image": "https://assets-in.bmscdn.com/discovery-catalog/events/tr:w-400,h-600,bg-CCCCCC:w-400.0,h-660.0,cm-pad_resize,bg-000000,fo-top:l-text,ie-U3VuLCAyMiBKdW4%3D,fs-29,co-FFFFFF,ly-612,lx-24,pa-8_0_0_0,l-end/et00439601-lmakdtcrrm-portrait.jpg"
  },
  {
    "name": "Kisi Ko Batana Mat Ft. Anubhav Singh Bassi",
    "url": " https://in.bookmyshow.com/events/anubhav-singh-bassi-new-material/ET00355125",
    "timestamp": "2025-06-11 08:36:42",
    "scraped_at": "2025-06-11T08:36:42.477204",
    "image": "https://assets-in.bmscdn.com/discovery-catalog/events/tr:w-400,h-600,bg-CCCCCC:w-400.0,h-660.0,cm-pad_resize,bg-000000,fo-top:l-text,ie-RnJpLCAyMCBKdW4gb253YXJkcw%3D%3D,fs-29,co-FFFFFF,ly-612,lx-24,pa-8_0_0_0,l-end/et00355125-vkjjlepyxr-portrait.jpg"
  },
  {
    "name": "Daily Ka Kaam Hai By Aakash Gupta",
    "url": " https://in.bookmyshow.com/events/excuse-me-brother-standup-solo-by-aakash-gupta/ET00347268",
    "timestamp": "2025-06-11 08:36:42",
    "scraped_at": "2025-06-11T08:36:42.512825",
    "image": "https://assets-in.bmscdn.com/discovery-catalog/events/tr:w-400,h-600,bg-CCCCCC:w-400.0,h-660.0,cm-pad_resize,bg-000000,fo-top:l-text,ie-RnJpLCAxMyBKdW4gb253YXJkcw%3D%3D,fs-29,co-FFFFFF,ly-612,lx-24,pa-8_0_0_0,l-end/et00347268-ndreddvblj-portrait.jpg"
  },
  {
    "name": "Gaurav Kapoor Live",
    "url": " https://in.bookmyshow.com/events/gaurav-kapoor-live/ET00317331",
    "timestamp": "2025-06-11 08:36:42",
    "scraped_at": "2025-06-11T08:36:42.547136",
    "image": "https://assets-in.bmscdn.com/discovery-catalog/events/tr:w-400,h-600,bg-CCCCCC:w-400.0,h-660.0,cm-pad_resize,bg-000000,fo-top:l-text,ie-RnJpLCAxMyBKdW4gb253YXJkcw%3D%3D,fs-29,co-FFFFFF,ly-612,lx-24,pa-8_0_0_0,l-end/et00317331-bmnnajgubr-portrait.jpg"
  },
  {
    "name": "Da Vinci Genius - Interactive Immersive Experience",
    "url": " https://in.bookmyshow.com/events/da-vinci-genius-interactive-immersive-experience/ET00440777",
    "timestamp": "2025-06-11 08:36:42",
    "scraped_at": "2025-06-11T08:36:42.580057",
    "image": "https://assets-in.bmscdn.com/discovery-catalog/events/tr:w-400,h-600,bg-CCCCCC:w-400.0,h-660.0,cm-pad_resize,bg-000000,fo-top:l-text,ie-V2VkLCAxMSBKdW4gb253YXJkcw%3D%3D,fs-29,co-FFFFFF,ly-612,lx-24,pa-8_0_0_0,l-end/et00440777-pbncdsuqdw-portrait.jpg"
  },
  {
    "name": "Bismil Ki Mehfil 2025 - Delhi",
    "url": " https://in.bookmyshow.com/events/bismil-ki-mehfil-2025-delhi/ET00443289",
    "timestamp": "2025-06-11 08:36:42",
    "scraped_at": "2025-06-11T08:36:42.613112",
    "image": "https://assets-in.bmscdn.com/discovery-catalog/events/tr:w-400,h-600,bg-CCCCCC:w-400.0,h-660.0,cm-pad_resize,bg-000000,fo-top:l-text,ie-U2F0LCAxMiBKdWw%3D,fs-29,co-FFFFFF,ly-612,lx-24,pa-8_0_0_0,l-end/et00443289-deuqamxhyw-portrait.jpg"
  },
  {
    "name": "Vipul Goyal-Unleashed",
    "url": " https://in.bookmyshow.com/events/vipul-goyal-live/ET00346737",
    "timestamp": "2025-06-11 08:36:42",
    "scraped_at": "2025-06-11T08:36:42.649188",
    "image": "https://assets-in.bmscdn.com/discovery-catalog/events/tr:w-400,h-600,bg-CCCCCC:w-400.0,h-660.0,cm-pad_resize,bg-000000,fo-top:l-text,ie-U2F0LCA1IEp1bCBvbndhcmRz,fs-29,co-FFFFFF,ly-612,lx-24,pa-8_0_0_0,l-end/et00346737-cbzhhwsvmt-portrait.jpg"
  },
  {
    "name": "Rambo Circus - Delhi",
    "url": " https://in.bookmyshow.com/events/rambo-circus/ET00332998",
    "timestamp": "2025-06-11 08:36:42",
    "scraped_at": "2025-06-11T08:36:42.685138",
    "image": "https://assets-in.bmscdn.com/discovery-catalog/events/tr:w-400,h-600,bg-CCCCCC:w-400.0,h-660.0,cm-pad_resize,bg-000000,fo-top:l-text,ie-RnJpLCAyNyBKdW4gb253YXJkcw%3D%3D,fs-29,co-FFFFFF,ly-612,lx-24,pa-8_0_0_0,l-end/et00332998-cymyglqxdy-portrait.jpg"
  },
  {
    "name": "Jo Bolta Hai Wohi Hota Hai Ft. Harsh Gujral",
    "url": " https://in.bookmyshow.com/events/jo-bolta-hai-wohi-hota-hai-ft-by-harsh-gujral/ET00319088",
    "timestamp": "2025-06-11 08:36:42",
    "scraped_at": "2025-06-11T08:36:42.717848",
    "image": "https://assets-in.bmscdn.com/discovery-catalog/events/tr:w-400,h-600,bg-CCCCCC:w-400.0,h-660.0,cm-pad_resize,bg-000000,fo-top:l-text,ie-TW9uLCAzMCBKdW4%3D,fs-29,co-FFFFFF,ly-612,lx-24,pa-8_0_0_0,l-end/et00319088-zqnukhfhxr-portrait.jpg"
  },
  {
    "name": "Comedy Nights Noida",
    "url": " https://in.bookmyshow.com/events/comedy-nights-noida/ET00407257",
    "timestamp": "2025-06-11 08:36:42",
    "scraped_at": "2025-06-11T08:36:42.751938",
    "image": "https://assets-in.bmscdn.com/discovery-catalog/events/tr:w-400,h-600,bg-CCCCCC:w-400.0,h-660.0,cm-pad_resize,bg-000000,fo-top:l-text,ie-V2VkLCAxMSBKdW4gb253YXJkcw%3D%3D,fs-29,co-FFFFFF,ly-612,lx-24,pa-8_0_0_0,l-end/et00407257-xhpfedbpba-portrait.jpg"
  },
  {
    "name": "Kenny Sebastian - A Crowd Work Show",
    "url": " https://in.bookmyshow.com/events/kenny-sebastian-a-crowd-work-show/ET00448339",
    "timestamp": "2025-06-11 08:36:42",
    "scraped_at": "2025-06-11T08:36:42.784637",
    "image": "https://assets-in.bmscdn.com/discovery-catalog/events/tr:w-400,h-600,bg-CCCCCC:w-400.0,h-660.0,cm-pad_resize,bg-000000,fo-top:l-text,ie-VGh1LCAxMiBKdW4%3D,fs-29,co-FFFFFF,ly-612,lx-24,pa-8_0_0_0,l-end/et00448339-wwvqnxrbpr-portrait.jpg"
  },
  {
    "name": "Best of Stand-up - Stand-up Comedy Show",
    "url": " https://in.bookmyshow.com/events/best-of-standup-inder-shreya-kd/ET00358274",
    "timestamp": "2025-06-11 08:36:42",
    "scraped_at": "2025-06-11T08:36:42.818770",
    "image": "https://assets-in.bmscdn.com/discovery-catalog/events/tr:w-400,h-600,bg-CCCCCC:w-400.0,h-660.0,cm-pad_resize,bg-000000,fo-top:l-text,ie-V2VkLCAxMSBKdW4gb253YXJkcw%3D%3D,fs-29,co-FFFFFF,ly-612,lx-24,pa-8_0_0_0,l-end/et00358274-ncjsdqzsef-portrait.jpg"
  },
  {
    "name": "SONU NIGAM LIVE IN CONCERT GURUGRAM",
    "url": " https://in.bookmyshow.com/events/sonu-nigam-live-in-concert-gurugram/ET00439782",
    "timestamp": "2025-06-11 08:36:42",
    "scraped_at": "2025-06-11T08:36:42.852999",
    "image": "https://assets-in.bmscdn.com/discovery-catalog/events/tr:w-400,h-600,bg-CCCCCC:w-400.0,h-660.0,cm-pad_resize,bg-000000,fo-top:l-text,ie-U2F0LCAxIE5vdg%3D%3D,fs-29,co-FFFFFF,ly-612,lx-24,pa-8_0_0_0,l-end/et00439782-nuqxzjwjtg-portrait.jpg"
  },
  {
    "name": "Telling Lies -A Standup Solo by Aashish Solanki",
    "url": " https://in.bookmyshow.com/events/aashish-solanki-live/ET00447106",
    "timestamp": "2025-06-11 08:36:42",
    "scraped_at": "2025-06-11T08:36:42.887091",
    "image": "https://assets-in.bmscdn.com/discovery-catalog/events/tr:w-400,h-600,bg-CCCCCC:w-400.0,h-660.0,cm-pad_resize,bg-000000,fo-top:l-text,ie-V2VkLCAyIEp1bA%3D%3D,fs-29,co-FFFFFF,ly-612,lx-24,pa-8_0_0_0,l-end/et00447106-rcxmpqsykm-portrait.jpg"
  },
  {
    "name": "Pratyush Chaubey Live",
    "url": " https://in.bookmyshow.com/events/papa-under-training-by-pratyush-chaubey/ET00397558",
    "timestamp": "2025-06-11 08:36:42",
    "scraped_at": "2025-06-11T08:36:42.920081",
    "image": "https://assets-in.bmscdn.com/discovery-catalog/events/tr:w-400,h-600,bg-CCCCCC:w-400.0,h-660.0,cm-pad_resize,bg-000000,fo-top:l-text,ie-U3VuLCAyMCBKdWw%3D,fs-29,co-FFFFFF,ly-612,lx-24,pa-8_0_0_0,l-end/et00397558-axnqepwjew-portrait.jpg"
  },
  {
    "name": "Comedy Nights @Comedy County",
    "url": " https://in.bookmyshow.com/events/comedy-nights-comedy-county/ET00446925",
    "timestamp": "2025-06-11 08:36:42",
    "scraped_at": "2025-06-11T08:36:42.952506",
    "image": "https://assets-in.bmscdn.com/discovery-catalog/events/tr:w-400,h-600,bg-CCCCCC:w-400.0,h-660.0,cm-pad_resize,bg-000000,fo-top:l-text,ie-V2VkLCAxMSBKdW4gb253YXJkcw%3D%3D,fs-29,co-FFFFFF,ly-612,lx-24,pa-8_0_0_0,l-end/et00446925-zuxvheegdj-portrait.jpg"
  },
  {
    "name": "Alien World at Airia Mall",
    "url": " https://in.bookmyshow.com/events/alien-world-at-airia-mall/ET00445888",
    "timestamp": "2025-06-11 08:36:42",
    "scraped_at": "2025-06-11T08:36:42.986115",
    "image": "https://assets-in.bmscdn.com/discovery-catalog/events/tr:w-400,h-600,bg-CCCCCC:w-400.0,h-660.0,cm-pad_resize,bg-000000,fo-top:l-text,ie-V2VkLCAxMSBKdW4gb253YXJkcw%3D%3D,fs-29,co-FFFFFF,ly-612,lx-24,pa-8_0_0_0,l-end/et00445888-bhszyadyze-portrait.jpg"
  },
  {
    "name": "Ravi Gupta Live : Birch Noida",
    "url": " https://in.bookmyshow.com/events/ravi-gupta-live-birch-noida/ET00446633",
    "timestamp": "2025-06-11 08:36:43",
    "scraped_at": "2025-06-11T08:36:43.022521",
    "image": "https://assets-in.bmscdn.com/discovery-catalog/events/tr:w-400,h-600,bg-CCCCCC:w-400.0,h-660.0,cm-pad_resize,bg-000000,fo-top:l-text,ie-RnJpLCAxMyBKdW4%3D,fs-29,co-FFFFFF,ly-612,lx-24,pa-8_0_0_0,l-end/et00446633-smcthsmudx-portrait.jpg"
  },
  {
    "name": "KidZania Delhi",
    "url": " https://in.bookmyshow.com/events/kidzania-delhi-tickets/ET00042240",
    "timestamp": "2025-06-11 08:36:43",
    "scraped_at": "2025-06-11T08:36:43.056419",
    "image": "https://assets-in.bmscdn.com/discovery-catalog/events/tr:w-400,h-600,bg-CCCCCC:w-400.0,h-660.0,cm-pad_resize,bg-000000,fo-top:l-text,ie-V2VkLCAxMSBKdW4gb253YXJkcw%3D%3D,fs-29,co-FFFFFF,ly-612,lx-24,pa-8_0_0_0,l-end/et00042240-fpntsplvze-portrait.jpg"
  },
  {
    "name": "Waqt Ki Baatein Tour by Dream Note",
    "url": " https://in.bookmyshow.com/events/waqt-ki-baatein-tour-by-dream-note/ET00449289",
    "timestamp": "2025-06-11 08:36:43",
    "scraped_at": "2025-06-11T08:36:43.089512",
    "image": "https://assets-in.bmscdn.com/discovery-catalog/events/tr:w-400,h-600,bg-CCCCCC:w-400.0,h-660.0,cm-pad_resize,bg-000000,fo-top:l-text,ie-RnJpLCAxIEF1Zw%3D%3D,fs-29,co-FFFFFF,ly-612,lx-24,pa-8_0_0_0,l-end/et00449289-ypxqbvbeem-portrait.jpg"
  },
  {
    "name": "A NIGHT OF LAUGHTER FT GAURAV GUPTA",
    "url": " https://in.bookmyshow.com/events/a-night-of-laughter-ft-gaurav-gupta/ET00400535",
    "timestamp": "2025-06-11 08:36:43",
    "scraped_at": "2025-06-11T08:36:43.123541",
    "image": "https://assets-in.bmscdn.com/discovery-catalog/events/tr:w-400,h-600,bg-CCCCCC:w-400.0,h-660.0,cm-pad_resize,bg-000000,fo-top:l-text,ie-U3VuLCAxMCBBdWc%3D,fs-29,co-FFFFFF,ly-612,lx-24,pa-8_0_0_0,l-end/et00400535-fhcgnbaeqb-portrait.jpg"
  },
  {
    "name": "Love, Death & Ketchup by Varun Grover",
    "url": " https://in.bookmyshow.com/events/love-death-ketchup-by-varun-grover/ET00448990",
    "timestamp": "2025-06-11 08:36:43",
    "scraped_at": "2025-06-11T08:36:43.168011",
    "image": "https://assets-in.bmscdn.com/discovery-catalog/events/tr:w-400,h-600,bg-CCCCCC:w-400.0,h-660.0,cm-pad_resize,bg-000000,fo-top:l-text,ie-U3VuLCAxMCBBdWc%3D,fs-29,co-FFFFFF,ly-612,lx-24,pa-8_0_0_0,l-end/et00448990-fpxsajbsjf-portrait.jpg"
  },
  {
    "name": "Nayab Midha Live",
    "url": " https://in.bookmyshow.com/events/the-nayab-show-ft-nayab-midha/ET00371345",
    "timestamp": "2025-06-11 08:36:43",
    "scraped_at": "2025-06-11T08:36:43.200712",
    "image": "https://assets-in.bmscdn.com/discovery-catalog/events/tr:w-400,h-600,bg-CCCCCC:w-400.0,h-660.0,cm-pad_resize,bg-000000,fo-top:l-text,ie-V2VkLCAxOCBKdW4%3D,fs-29,co-FFFFFF,ly-612,lx-24,pa-8_0_0_0,l-end/et00371345-veenqdubwf-portrait.jpg"
  },
  {
    "name": "Blind Date",
    "url": " https://in.bookmyshow.com/events/blindfolded-conversations/ET00361919",
    "timestamp": "2025-06-11 08:36:43",
    "scraped_at": "2025-06-11T08:36:43.233189",
    "image": "https://assets-in.bmscdn.com/discovery-catalog/events/tr:w-400,h-600,bg-CCCCCC:w-400.0,h-660.0,cm-pad_resize,bg-000000,fo-top:l-text,ie-U2F0LCAxNCBKdW4gb253YXJkcw%3D%3D,fs-29,co-FFFFFF,ly-612,lx-24,pa-8_0_0_0,l-end/et00361919-ppexyfqgud-portrait.jpg"
  },
  {
    "name": "PS - I Love You By Pranav Sharma",
    "url": " https://in.bookmyshow.com/events/taaza-phool-ft-pranav-sharma/ET00408533",
    "timestamp": "2025-06-11 08:36:43",
    "scraped_at": "2025-06-11T08:36:43.285734",
    "image": "https://assets-in.bmscdn.com/discovery-catalog/events/tr:w-400,h-600,bg-CCCCCC:w-400.0,h-660.0,cm-pad_resize,bg-000000,fo-top:l-text,ie-U2F0LCAyMSBKdW4gb253YXJkcw%3D%3D,fs-29,co-FFFFFF,ly-612,lx-24,pa-8_0_0_0,l-end/et00408533-cqtrzlpwaq-portrait.jpg"
  },
  {
    "name": "Swiftchella - A Taylor Swift-Themed Fan Party",
    "url": " https://in.bookmyshow.com/events/swiftchella-a-taylor-swift-themed-fan-party/ET00441036",
    "timestamp": "2025-06-11 08:36:43",
    "scraped_at": "2025-06-11T08:36:43.318676",
    "image": "https://assets-in.bmscdn.com/discovery-catalog/events/tr:w-400,h-600,bg-CCCCCC:w-400.0,h-660.0,cm-pad_resize,bg-000000,fo-top:l-text,ie-U3VuLCA2IEp1bA%3D%3D,fs-29,co-FFFFFF,ly-612,lx-24,pa-8_0_0_0,l-end/et00441036-ulxvezwwlu-portrait.jpg"
  },
  {
    "name": "Comedy Show Noida Sector 18",
    "url": " https://in.bookmyshow.com/events/comedy-show-noida-sector-18/ET00448749",
    "timestamp": "2025-06-11 08:36:43",
    "scraped_at": "2025-06-11T08:36:43.355028",
    "image": "https://assets-in.bmscdn.com/discovery-catalog/events/tr:w-400,h-600,bg-CCCCCC:w-400.0,h-660.0,cm-pad_resize,bg-000000,fo-top:l-text,ie-V2VkLCAxMSBKdW4gb253YXJkcw%3D%3D,fs-29,co-FFFFFF,ly-612,lx-24,pa-8_0_0_0,l-end/et00448749-xnxmyffwbp-portrait.jpg"
  },
  {
    "name": "Adult Standup Comedy Show",
    "url": " https://in.bookmyshow.com/events/adult-standup-comedy-show/ET00440230",
    "timestamp": "2025-06-11 08:36:43",
    "scraped_at": "2025-06-11T08:36:43.391542",
    "image": "https://assets-in.bmscdn.com/discovery-catalog/events/tr:w-400,h-600,bg-CCCCCC:w-400.0,h-660.0,cm-pad_resize,bg-000000,fo-top:l-text,ie-V2VkLCAxMSBKdW4gb253YXJkcw%3D%3D,fs-29,co-FFFFFF,ly-612,lx-24,pa-8_0_0_0,l-end/et00440230-tfvabnqked-portrait.jpg"
  }
]